forced_url_modifier/__init__.py
forced_url_modifier/core.py
forced_url_modifier-0.0.7.dist-info/METADATA
forced_url_modifier-0.0.7.dist-info/WHEEL
forced_url_modifier-0.0.7.dist-info/top_level.txt
forced_url_modifier-0.0.7.dist-info/RECORD
