Metadata-Version: 2.1
Name: forced-url-modifier
Version: 0.0.7
Summary: for URL forced FULL encoding & decoding
Home-page: https://github.com/khgxsss/forced-url-modifier
Author: dh kim
Author-email: itschoolkdh@gmail.com
Classifier: Programming Language :: Python :: 3
Classifier: License :: OSI Approved :: MIT License
Classifier: Operating System :: OS Independent
Requires-Python: >=3.5
